pyqir/__init__.py
pyqir/_basicqis.py
pyqir/_constants.py
pyqir/_entry_point.py
pyqir/_native.abi3.so
pyqir/_native.pyi
pyqir/_passes.py
pyqir/_simple.py
pyqir/py.typed
pyqir/qis.py
pyqir/rt.py
pyqir-0.12.3.dist-info/METADATA
pyqir-0.12.3.dist-info/WHEEL
pyqir-0.12.3.dist-info/RECORD
pyqir-0.12.3.dist-info/licenses/LICENSE
pyqir-0.12.3.dist-info/licenses/NOTICE-WHEEL.txt
