Metadata-Version: 2.4
Name: pyqir
Version: 0.12.3
Classifier: License :: OSI Approved :: MIT License
Classifier: Development Status :: 3 - Alpha
Classifier: Intended Audience :: Developers
Classifier: Programming Language :: Python :: 3.9
Classifier: Programming Language :: Python :: 3.10
Classifier: Programming Language :: Python :: 3.11
Classifier: Programming Language :: Python :: 3.12
Classifier: Programming Language :: Python :: 3.13
Classifier: Programming Language :: Python
Classifier: Programming Language :: Rust
Classifier: Operating System :: MacOS
Classifier: Operating System :: Microsoft :: Windows
Classifier: Operating System :: POSIX :: Linux
Requires-Dist: pytest~=7.2.0 ; extra == 'test'
Provides-Extra: test
License-File: LICENSE
License-File: NOTICE-WHEEL.txt
Summary: PyQIR parses, generates and evaluates the Quantum Intermediate Representation.
Home-Page: https://github.com/qir-alliance/pyqir
Author: Microsoft
License: MIT
Requires-Python: >=3.9
Project-URL: Source Code, https://github.com/qir-alliance/pyqir
